sentinel_ai/__init__.py
sentinel_ai/bias/__init__.py
sentinel_ai/bias/scanner.py
sentinel_ai/poison/__init__.py
sentinel_ai/poison/detector.py
sentinel_ai/poison/utils.py
sentinel_ai/prompt/__init__.py
sentinel_ai/prompt/scanner.py
sentinel_ai-0.2.0.dist-info/METADATA
sentinel_ai-0.2.0.dist-info/WHEEL
sentinel_ai-0.2.0.dist-info/top_level.txt
sentinel_ai-0.2.0.dist-info/RECORD
